smalldiffusion/__init__.py
smalldiffusion/data.py
smalldiffusion/diffusion.py
smalldiffusion/model.py
smalldiffusion/model_dit.py
smalldiffusion/model_unet.py
smalldiffusion-0.4.4.dist-info/licenses/LICENSE
smalldiffusion-0.4.4.dist-info/METADATA
smalldiffusion-0.4.4.dist-info/WHEEL
smalldiffusion-0.4.4.dist-info/top_level.txt
smalldiffusion-0.4.4.dist-info/RECORD
