Metadata-Version: 2.4
Name: smalldiffusion
Version: 0.4.4
Summary: A minimal but functional implementation of diffusion model training and sampling
Author-email: Chenyang Yuan <yuanchenyang@gmail.com>
Maintainer-email: Chenyang Yuan <yuanchenyang@gmail.com>
License: Copyright 2023-2024 Chenyang Yuan
Project-URL: Homepage, https://github.com/yuanchenyang/smalldiffusion
Project-URL: Bug Tracker, https://github.com/yuanchenyang/smalldiffusion/issues
Project-URL: Documentation, https://github.com/yuanchenyang/smalldiffusion
Project-URL: Source, https://github.com/yuanchenyang/smalldiffusion
Classifier: Development Status :: 4 - Beta
Classifier: License :: OSI Approved :: MIT License
Classifier: Programming Language :: Python :: 3
Classifier: Operating System :: OS Independent
Requires-Python: >=3.10
License-File: LICENSE
Requires-Dist: accelerate
Requires-Dist: numpy
Requires-Dist: torchvision
Requires-Dist: torch
Requires-Dist: tqdm
Requires-Dist: einops
Provides-Extra: dev
Requires-Dist: build; extra == "dev"
Requires-Dist: twine; extra == "dev"
Provides-Extra: test
Requires-Dist: pytest; extra == "test"
Requires-Dist: diffusers==0.32.1; extra == "test"
Provides-Extra: examples
Requires-Dist: einops; extra == "examples"
Requires-Dist: diffusers; extra == "examples"
Requires-Dist: transformers; extra == "examples"
Requires-Dist: datasets; extra == "examples"
Requires-Dist: jupyter; extra == "examples"
Requires-Dist: matplotlib; extra == "examples"
Requires-Dist: torch_ema; extra == "examples"
Dynamic: license-file
